[{"line":1,"elements":[{"line":2,"name":"","description":"","type":"background","keyword":"Background","steps":[{"result":{"duration":2771000000,"status":"passed"},"line":3,"name":"user navigate to home page","match":{"location":"stepDefinitions.HomePageStepDefinition.openHomePage()"},"keyword":"Given "},{"result":{"duration":2199000000,"status":"passed"},"line":4,"name":"user clicked on register link","match":{"location":"stepDefinitions.RegistrationStepDefinition.clickOnRegisterButton()"},"keyword":"And "}]},{"start_timestamp":"2022-09-12T18:29:13.358Z","before":[{"result":{"duration":4489000000,"status":"passed"},"match":{"location":"stepDefinitions.Hooks.openChromeBrowser()"}}],"line":7,"name":"SC1- User could register with valid data","description":"","id":"sc1--user-registration;sc1--user-could-register-with-valid-data","after":[{"result":{"duration":795000000,"status":"passed"},"match":{"location":"stepDefinitions.Hooks.tearDown()"}}],"type":"scenario","keyword":"Scenario","steps":[{"result":{"duration":70000000,"status":"passed"},"line":8,"name":"user selected gender","match":{"location":"stepDefinitions.RegistrationStepDefinition.selectGender()"},"keyword":"When "},{"result":{"duration":90000000,"status":"passed"},"line":9,"name":"user entered first name","match":{"location":"stepDefinitions.RegistrationStepDefinition.enterFirstName()"},"keyword":"And "},{"result":{"duration":105000000,"status":"passed"},"line":10,"name":"user entered last name","match":{"location":"stepDefinitions.RegistrationStepDefinition.enterLastName()"},"keyword":"And "},{"result":{"duration":336000000,"status":"passed"},"line":11,"name":"user selected birth of date","match":{"location":"stepDefinitions.RegistrationStepDefinition.enterBirthOfDate()"},"keyword":"And "},{"result":{"duration":117000000,"status":"passed"},"line":12,"name":"user entered email for registration","match":{"location":"stepDefinitions.RegistrationStepDefinition.enterEmail()"},"keyword":"And "},{"result":{"duration":95000000,"status":"passed"},"line":13,"name":"user entered company name","match":{"location":"stepDefinitions.RegistrationStepDefinition.enterCompanyName()"},"keyword":"And "},{"result":{"duration":92000000,"status":"passed"},"line":14,"name":"user entered password for registration","match":{"location":"stepDefinitions.RegistrationStepDefinition.enterPassword()"},"keyword":"And "},{"result":{"duration":99000000,"status":"passed"},"line":15,"name":"user confirmed password for registration","match":{"location":"stepDefinitions.RegistrationStepDefinition.confirmPassword()"},"keyword":"And "},{"result":{"duration":1315000000,"status":"passed"},"line":16,"name":"user clicked on register button","match":{"location":"stepDefinitions.RegistrationStepDefinition.userClickedOnRegisterButton()"},"keyword":"And "},{"result":{"duration":66000000,"status":"passed"},"line":17,"name":"user should have a success message for registration","match":{"location":"stepDefinitions.RegistrationStepDefinition.userShouldHaveASuccessMessageForRegistration()"},"keyword":"Then "}],"tags":[{"name":"@scenario1"}]}],"name":"SC1- User registration","description":"","id":"sc1--user-registration","keyword":"Feature","uri":"file:src/main/resources/features/SC01-registration.feature","tags":[]},{"line":1,"elements":[{"line":2,"name":"","description":"","type":"background","keyword":"Background","steps":[{"result":{"duration":1629000000,"status":"passed"},"line":3,"name":"user navigate to home page","match":{"location":"stepDefinitions.HomePageStepDefinition.openHomePage()"},"keyword":"Given "}]},{"start_timestamp":"2022-09-12T18:29:26.052Z","before":[{"result":{"duration":1632000000,"status":"passed"},"match":{"location":"stepDefinitions.Hooks.openChromeBrowser()"}}],"line":7,"name":"SC2- User could log in with valid email and password","description":"","id":"sc2--user-could-log-in;sc2--user-could-log-in-with-valid-email-and-password","after":[{"result":{"duration":734000000,"status":"passed"},"match":{"location":"stepDefinitions.Hooks.tearDown()"}}],"type":"scenario","keyword":"Scenario","steps":[{"result":{"duration":2112000000,"status":"passed"},"line":8,"name":"user clicked on login link","match":{"location":"stepDefinitions.LoginStepDefinition.userClickedOnLoginLink()"},"keyword":"And "},{"result":{"duration":107000000,"status":"passed"},"line":9,"name":"user entered email for login","match":{"location":"stepDefinitions.LoginStepDefinition.userEnteredEmailForLogin()"},"keyword":"And "},{"result":{"duration":88000000,"status":"passed"},"line":10,"name":"user entered password for login","match":{"location":"stepDefinitions.LoginStepDefinition.userEnteredPasswordForLogin()"},"keyword":"And "},{"result":{"duration":4061000000,"status":"passed"},"line":11,"name":"user clicked on login button","match":{"location":"stepDefinitions.LoginStepDefinition.userClickedOnLoginButton()"},"keyword":"And "},{"result":{"duration":80000000,"status":"passed"},"line":12,"name":"user should have a success message for login","match":{"location":"stepDefinitions.LoginStepDefinition.userShouldHaveASuccessMessageForLogin()"},"keyword":"Then "}],"tags":[{"name":"@scenario2"}]}],"name":"SC2- User could log in","description":"","id":"sc2--user-could-log-in","keyword":"Feature","uri":"file:src/main/resources/features/SC02-login.feature","tags":[]},{"line":1,"elements":[{"line":2,"name":"","description":"","type":"background","keyword":"Background","steps":[{"result":{"duration":1885000000,"status":"passed"},"line":3,"name":"user navigate to home page","match":{"location":"stepDefinitions.HomePageStepDefinition.openHomePage()"},"keyword":"Given "},{"result":{"duration":1075000000,"status":"passed"},"line":4,"name":"user clicked on login link","match":{"location":"stepDefinitions.LoginStepDefinition.userClickedOnLoginLink()"},"keyword":"And "}]},{"start_timestamp":"2022-09-12T18:29:36.528Z","before":[{"result":{"duration":1544000000,"status":"passed"},"match":{"location":"stepDefinitions.Hooks.openChromeBrowser()"}}],"line":7,"name":"SC3- User could reset his/her password successfully","description":"","id":"sc3--user-could-reset-his/her-password;sc3--user-could-reset-his/her-password-successfully","after":[{"result":{"duration":710000000,"status":"passed"},"match":{"location":"stepDefinitions.Hooks.tearDown()"}}],"type":"scenario","keyword":"Scenario","steps":[{"result":{"duration":872000000,"status":"passed"},"line":8,"name":"user clicked on forgot password","match":{"location":"stepDefinitions.PasswordRecoveryStepDefinition.userClickedOnForgotPassword()"},"keyword":"And "},{"result":{"duration":117000000,"status":"passed"},"line":9,"name":"user entered email for reset password","match":{"location":"stepDefinitions.PasswordRecoveryStepDefinition.userEnteredEmailForResetPassword()"},"keyword":"And "},{"result":{"duration":627000000,"status":"passed"},"line":10,"name":"user clicked on recover button","match":{"location":"stepDefinitions.PasswordRecoveryStepDefinition.userClickedOnRecoverButton()"},"keyword":"And "},{"result":{"duration":37000000,"status":"passed"},"line":11,"name":"user should have a success message for recover","match":{"location":"stepDefinitions.PasswordRecoveryStepDefinition.userShouldHaveASuccessMessageForRecover()"},"keyword":"Then "}],"tags":[{"name":"@scenario3"}]}],"name":"SC3- User could reset his/her password","description":"","id":"sc3--user-could-reset-his/her-password","keyword":"Feature","uri":"file:src/main/resources/features/SC03-passwordRecovery.feature","tags":[]},{"line":1,"elements":[{"line":2,"name":"","description":"","type":"background","keyword":"Background","steps":[{"result":{"duration":1327000000,"status":"passed"},"line":3,"name":"user navigate to home page","match":{"location":"stepDefinitions.HomePageStepDefinition.openHomePage()"},"keyword":"Given "}]},{"start_timestamp":"2022-09-12T18:29:43.443Z","before":[{"result":{"duration":1574000000,"status":"passed"},"match":{"location":"stepDefinitions.Hooks.openChromeBrowser()"}}],"line":6,"name":"SC4- Logged User could search for any product","description":"","id":"sc4--logged-user-could-search;sc4--logged-user-could-search-for-any-product","after":[{"result":{"duration":738000000,"status":"passed"},"match":{"location":"stepDefinitions.Hooks.tearDown()"}}],"type":"scenario","keyword":"Scenario","steps":[{"result":{"duration":1178000000,"status":"passed"},"line":7,"name":"user clicked on login link","match":{"location":"stepDefinitions.LoginStepDefinition.userClickedOnLoginLink()"},"keyword":"And "},{"result":{"duration":105000000,"status":"passed"},"line":8,"name":"user entered email for login","match":{"location":"stepDefinitions.LoginStepDefinition.userEnteredEmailForLogin()"},"keyword":"And "},{"result":{"duration":90000000,"status":"passed"},"line":9,"name":"user entered password for login","match":{"location":"stepDefinitions.LoginStepDefinition.userEnteredPasswordForLogin()"},"keyword":"And "},{"result":{"duration":4093000000,"status":"passed"},"line":10,"name":"user clicked on login button","match":{"location":"stepDefinitions.LoginStepDefinition.userClickedOnLoginButton()"},"keyword":"And "},{"result":{"duration":86000000,"status":"passed"},"line":11,"name":"user enter name of item to search for","match":{"location":"stepDefinitions.SearchStepDefinition.userEnterNameOfItemToSearchFor()"},"keyword":"And "},{"result":{"duration":3964000000,"status":"passed"},"line":12,"name":"user clicked on search button","match":{"location":"stepDefinitions.SearchStepDefinition.userClickedOnSearchButton()"},"keyword":"And "},{"result":{"duration":62000000,"status":"passed"},"line":13,"name":"user should have products contains the searched word","match":{"location":"stepDefinitions.SearchStepDefinition.userShouldHaveProductsContainsTheSearchedWord()"},"keyword":"Then "}],"tags":[{"name":"@scenario4"}]}],"name":"SC4- Logged User could search","description":"","id":"sc4--logged-user-could-search","keyword":"Feature","uri":"file:src/main/resources/features/SC04-search.feature","tags":[]},{"line":1,"elements":[{"line":2,"name":"","description":"","type":"background","keyword":"Background","steps":[{"result":{"duration":1811000000,"status":"passed"},"line":3,"name":"user navigate to home page","match":{"location":"stepDefinitions.HomePageStepDefinition.openHomePage()"},"keyword":"Given "},{"result":{"duration":1030000000,"status":"passed"},"line":4,"name":"user clicked on login link","match":{"location":"stepDefinitions.LoginStepDefinition.userClickedOnLoginLink()"},"keyword":"And "},{"result":{"duration":105000000,"status":"passed"},"line":5,"name":"user entered email for login","match":{"location":"stepDefinitions.LoginStepDefinition.userEnteredEmailForLogin()"},"keyword":"And "},{"result":{"duration":90000000,"status":"passed"},"line":6,"name":"user entered password for login","match":{"location":"stepDefinitions.LoginStepDefinition.userEnteredPasswordForLogin()"},"keyword":"And "},{"result":{"duration":4116000000,"status":"passed"},"line":7,"name":"user clicked on login button","match":{"location":"stepDefinitions.LoginStepDefinition.userClickedOnLoginButton()"},"keyword":"And "}]},{"start_timestamp":"2022-09-12T18:29:56.683Z","before":[{"result":{"duration":1725000000,"status":"passed"},"match":{"location":"stepDefinitions.Hooks.openChromeBrowser()"}}],"line":10,"name":"SC5- Logged User could switch between currencies US-Euro","description":"","id":"sc5--logged-user-could-switch-between-currencies;sc5--logged-user-could-switch-between-currencies-us-euro","after":[{"result":{"duration":1233000000,"status":"passed"},"match":{"location":"stepDefinitions.Hooks.tearDown()"}}],"type":"scenario","keyword":"Scenario","steps":[{"result":{"duration":1149000000,"status":"passed"},"line":11,"name":"user change currency from usd to euro","match":{"location":"stepDefinitions.ChangeCurrencyStepDefinition.userChangeCurrencyFromUsdToEuro()"},"keyword":"And "},{"result":{"duration":51000000,"status":"passed"},"line":12,"name":"all products shown are in euro","match":{"location":"stepDefinitions.ChangeCurrencyStepDefinition.allProductsShownAreInEuro()"},"keyword":"Then "}],"tags":[{"name":"@scenario5"}]}],"name":"SC5- Logged User could switch between currencies","description":"","id":"sc5--logged-user-could-switch-between-currencies","keyword":"Feature","uri":"file:src/main/resources/features/SC05-currencyChange.feature","tags":[]},{"line":1,"elements":[{"line":2,"name":"","description":"","type":"background","keyword":"Background","steps":[{"result":{"duration":2058000000,"status":"passed"},"line":3,"name":"user navigate to home page","match":{"location":"stepDefinitions.HomePageStepDefinition.openHomePage()"},"keyword":"Given "},{"result":{"duration":983000000,"status":"passed"},"line":4,"name":"user clicked on login link","match":{"location":"stepDefinitions.LoginStepDefinition.userClickedOnLoginLink()"},"keyword":"And "},{"result":{"duration":109000000,"status":"passed"},"line":5,"name":"user entered email for login","match":{"location":"stepDefinitions.LoginStepDefinition.userEnteredEmailForLogin()"},"keyword":"And "},{"result":{"duration":89000000,"status":"passed"},"line":6,"name":"user entered password for login","match":{"location":"stepDefinitions.LoginStepDefinition.userEnteredPasswordForLogin()"},"keyword":"And "},{"result":{"duration":4096000000,"status":"passed"},"line":7,"name":"user clicked on login button","match":{"location":"stepDefinitions.LoginStepDefinition.userClickedOnLoginButton()"},"keyword":"And "}]},{"start_timestamp":"2022-09-12T18:30:08.039Z","before":[{"result":{"duration":1523000000,"status":"passed"},"match":{"location":"stepDefinitions.Hooks.openChromeBrowser()"}}],"line":10,"name":"SC6- Logged user could select different Categories","description":"","id":"sc6--logged-user-could-select-different-categories;sc6--logged-user-could-select-different-categories","after":[{"result":{"duration":1197000000,"status":"passed"},"match":{"location":"stepDefinitions.Hooks.tearDown()"}}],"type":"scenario","keyword":"Scenario","steps":[{"result":{"duration":160000000,"status":"passed"},"line":11,"name":"user hover on electronic category","match":{"location":"stepDefinitions.SelectDifferentCategories.userHoverOnElectronicCategory()"},"keyword":"And "},{"result":{"duration":970000000,"status":"passed"},"line":12,"name":"user click on cellPhone category","match":{"location":"stepDefinitions.SelectDifferentCategories.userClickOnCellPhoneCategory()"},"keyword":"And "},{"result":{"duration":6000000,"status":"passed"},"line":13,"name":"cell phones page should appear to the user","match":{"location":"stepDefinitions.SelectDifferentCategories.cellPhonesAppear()"},"keyword":"Then "}],"tags":[{"name":"@scenario6"}]}],"name":"SC6- Logged user could select different Categories","description":"","id":"sc6--logged-user-could-select-different-categories","keyword":"Feature","uri":"file:src/main/resources/features/SC06-selectDifferentCategories.feature","tags":[]},{"line":1,"elements":[{"line":3,"name":"","description":"","type":"background","keyword":"Background","steps":[{"result":{"duration":3485000000,"status":"passed"},"line":4,"name":"user navigate to home page","match":{"location":"stepDefinitions.HomePageStepDefinition.openHomePage()"},"keyword":"Given "},{"result":{"duration":1034000000,"status":"passed"},"line":5,"name":"user clicked on login link","match":{"location":"stepDefinitions.LoginStepDefinition.userClickedOnLoginLink()"},"keyword":"And "},{"result":{"duration":106000000,"status":"passed"},"line":6,"name":"user entered email for login","match":{"location":"stepDefinitions.LoginStepDefinition.userEnteredEmailForLogin()"},"keyword":"And "},{"result":{"duration":87000000,"status":"passed"},"line":7,"name":"user entered password for login","match":{"location":"stepDefinitions.LoginStepDefinition.userEnteredPasswordForLogin()"},"keyword":"And "},{"result":{"duration":4080000000,"status":"passed"},"line":8,"name":"user clicked on login button","match":{"location":"stepDefinitions.LoginStepDefinition.userClickedOnLoginButton()"},"keyword":"And "}]},{"start_timestamp":"2022-09-12T18:30:19.260Z","before":[{"result":{"duration":1577000000,"status":"passed"},"match":{"location":"stepDefinitions.Hooks.openChromeBrowser()"}}],"line":11,"name":"SC7- Logged user could filter with red color","description":"","id":"sc7--logged-user-could-filter-with-color;sc7--logged-user-could-filter-with-red-color","after":[{"result":{"duration":1210000000,"status":"passed"},"match":{"location":"stepDefinitions.Hooks.tearDown()"}}],"type":"scenario","keyword":"Scenario","steps":[{"result":{"duration":143000000,"status":"passed"},"line":12,"name":"user hover on apparel category","match":{"location":"stepDefinitions.ChangeColorFilter.userHoverOnAppearlCategory()"},"keyword":"And "},{"result":{"duration":967000000,"status":"passed"},"line":13,"name":"user click on shoes category","match":{"location":"stepDefinitions.ChangeColorFilter.userClickOnShoesCategory()"},"keyword":"And "},{"result":{"duration":84000000,"status":"passed"},"line":14,"name":"user change color to red","match":{"location":"stepDefinitions.ChangeColorFilter.userChangeColorToRed()"},"keyword":"And "},{"result":{"duration":26000000,"status":"passed"},"line":15,"name":"shoes with red color only should appear to the user","match":{"location":"stepDefinitions.ChangeColorFilter.shoesWithRedColorOnlyShouldAppearToTheUser()"},"keyword":"Then "}],"tags":[{"name":"@scenario7"}]}],"name":"SC7- Logged user could filter with color","description":"","id":"sc7--logged-user-could-filter-with-color","keyword":"Feature","uri":"file:src/main/resources/features/SC07-filterWithColor.feature","tags":[]},{"line":1,"elements":[{"line":2,"name":"","description":"","type":"background","keyword":"Background","steps":[{"result":{"duration":1988000000,"status":"passed"},"line":3,"name":"user navigate to home page","match":{"location":"stepDefinitions.HomePageStepDefinition.openHomePage()"},"keyword":"Given "},{"result":{"duration":995000000,"status":"passed"},"line":4,"name":"user clicked on login link","match":{"location":"stepDefinitions.LoginStepDefinition.userClickedOnLoginLink()"},"keyword":"And "},{"result":{"duration":102000000,"status":"passed"},"line":5,"name":"user entered email for login","match":{"location":"stepDefinitions.LoginStepDefinition.userEnteredEmailForLogin()"},"keyword":"And "},{"result":{"duration":88000000,"status":"passed"},"line":6,"name":"user entered password for login","match":{"location":"stepDefinitions.LoginStepDefinition.userEnteredPasswordForLogin()"},"keyword":"And "},{"result":{"duration":4070000000,"status":"passed"},"line":7,"name":"user clicked on login button","match":{"location":"stepDefinitions.LoginStepDefinition.userClickedOnLoginButton()"},"keyword":"And "}]},{"start_timestamp":"2022-09-12T18:30:32.091Z","before":[{"result":{"duration":1606000000,"status":"passed"},"match":{"location":"stepDefinitions.Hooks.openChromeBrowser()"}}],"line":10,"name":"SC8- Logged user could select awesome tag","description":"","id":"sc8--logged-user-could-select-different-tags;sc8--logged-user-could-select-awesome-tag","after":[{"result":{"duration":1393000000,"status":"passed"},"match":{"location":"stepDefinitions.Hooks.tearDown()"}}],"type":"scenario","keyword":"Scenario","steps":[{"result":{"duration":1110000000,"status":"passed"},"line":11,"name":"user open search page","match":{"location":"stepDefinitions.SelectDifferentTags.userOpenSearchPage()"},"keyword":"And "},{"result":{"duration":1283000000,"status":"passed"},"line":12,"name":"user choose awesome tag","match":{"location":"stepDefinitions.SelectDifferentTags.userChooseAwesomeTag()"},"keyword":"And "},{"result":{"duration":13000000,"status":"passed"},"line":13,"name":"awesome products page should appear to the user","match":{"location":"stepDefinitions.SelectDifferentTags.awesomeProductAppear()"},"keyword":"Then "}],"tags":[{"name":"@scenario8"}]}],"name":"SC8- Logged user could select different tags","description":"","id":"sc8--logged-user-could-select-different-tags","keyword":"Feature","uri":"file:src/main/resources/features/SC08-selectDifferentTags.feature","tags":[]},{"line":1,"elements":[{"line":2,"name":"","description":"","type":"background","keyword":"Background","steps":[{"result":{"duration":2063000000,"status":"passed"},"line":3,"name":"user navigate to home page","match":{"location":"stepDefinitions.HomePageStepDefinition.openHomePage()"},"keyword":"Given "},{"result":{"duration":1206000000,"status":"passed"},"line":4,"name":"user clicked on login link","match":{"location":"stepDefinitions.LoginStepDefinition.userClickedOnLoginLink()"},"keyword":"And "},{"result":{"duration":99000000,"status":"passed"},"line":5,"name":"user entered email for login","match":{"location":"stepDefinitions.LoginStepDefinition.userEnteredEmailForLogin()"},"keyword":"And "},{"result":{"duration":88000000,"status":"passed"},"line":6,"name":"user entered password for login","match":{"location":"stepDefinitions.LoginStepDefinition.userEnteredPasswordForLogin()"},"keyword":"And "},{"result":{"duration":4091000000,"status":"passed"},"line":7,"name":"user clicked on login button","match":{"location":"stepDefinitions.LoginStepDefinition.userClickedOnLoginButton()"},"keyword":"And "},{"result":{"duration":1151000000,"status":"passed"},"line":8,"name":"user navigate to books pages","match":{"location":"stepDefinitions.AddToShoppingCart.userNavigateToBooksPages()"},"keyword":"And "}]},{"start_timestamp":"2022-09-12T18:30:44.760Z","before":[{"result":{"duration":1484000000,"status":"passed"},"match":{"location":"stepDefinitions.Hooks.openChromeBrowser()"}}],"line":11,"name":"SC9- Logged user could add different products to Shopping cart","description":"","id":"sc9--logged-user-could-add-different-products-to-shopping-cart;sc9--logged-user-could-add-different-products-to-shopping-cart","after":[{"result":{"duration":767000000,"status":"passed"},"match":{"location":"stepDefinitions.Hooks.tearDown()"}}],"type":"scenario","keyword":"Scenario","steps":[{"result":{"duration":15219000000,"status":"passed"},"line":12,"name":"user add items to shopping cart","match":{"location":"stepDefinitions.AddToShoppingCart.userAddItemsToShoppingCart()"},"keyword":"And "},{"result":{"duration":1334000000,"status":"passed"},"line":13,"name":"user navigate to shopping cart","match":{"location":"stepDefinitions.AddToShoppingCart.userNavigateToShopingCart()"},"keyword":"And "},{"result":{"duration":6236000000,"status":"passed"},"line":14,"name":"added items should appear at shopping cart","match":{"location":"stepDefinitions.AddToShoppingCart.addedItemsShouldAppearAtShoppingCart()"},"keyword":"Then "}],"tags":[{"name":"@scenario9"}]}],"name":"SC9- Logged user could add different products to Shopping cart","description":"","id":"sc9--logged-user-could-add-different-products-to-shopping-cart","keyword":"Feature","uri":"file:src/main/resources/features/SC09-addDifferentProductsToShoppingCart.feature","tags":[]},{"line":1,"elements":[{"line":3,"name":"","description":"","type":"background","keyword":"Background","steps":[{"result":{"duration":2006000000,"status":"passed"},"line":4,"name":"user navigate to home page","match":{"location":"stepDefinitions.HomePageStepDefinition.openHomePage()"},"keyword":"Given "},{"result":{"duration":953000000,"status":"passed"},"line":5,"name":"user clicked on login link","match":{"location":"stepDefinitions.LoginStepDefinition.userClickedOnLoginLink()"},"keyword":"And "},{"result":{"duration":104000000,"status":"passed"},"line":6,"name":"user entered email for login","match":{"location":"stepDefinitions.LoginStepDefinition.userEnteredEmailForLogin()"},"keyword":"And "},{"result":{"duration":89000000,"status":"passed"},"line":7,"name":"user entered password for login","match":{"location":"stepDefinitions.LoginStepDefinition.userEnteredPasswordForLogin()"},"keyword":"And "},{"result":{"duration":4122000000,"status":"passed"},"line":8,"name":"user clicked on login button","match":{"location":"stepDefinitions.LoginStepDefinition.userClickedOnLoginButton()"},"keyword":"And "},{"result":{"duration":1208000000,"status":"passed"},"line":9,"name":"user navigate to books pages","match":{"location":"stepDefinitions.AddToShoppingCart.userNavigateToBooksPages()"},"keyword":"And "}]},{"start_timestamp":"2022-09-12T18:31:18.532Z","before":[{"result":{"duration":1535000000,"status":"passed"},"match":{"location":"stepDefinitions.Hooks.openChromeBrowser()"}}],"line":12,"name":"SC10- Logged user could add different products to Wishlist","description":"","id":"sc10--logged-user-could-add-different-products-to-wishlist;sc10--logged-user-could-add-different-products-to-wishlist","after":[{"result":{"duration":731000000,"status":"passed"},"match":{"location":"stepDefinitions.Hooks.tearDown()"}}],"type":"scenario","keyword":"Scenario","steps":[{"result":{"duration":15236000000,"status":"passed"},"line":13,"name":"user add items to whish list","match":{"location":"stepDefinitions.AddToWishList.userAddItemsToWhishList()"},"keyword":"And "},{"result":{"duration":1271000000,"status":"passed"},"line":14,"name":"user navigate to whish list","match":{"location":"stepDefinitions.AddToWishList.userNavigateToWhishList()"},"keyword":"And "},{"result":{"duration":6183000000,"status":"passed"},"line":15,"name":"added items should appear at whish list","match":{"location":"stepDefinitions.AddToWishList.addedItemsShouldAppearAtWhishList()"},"keyword":"Then "}],"tags":[{"name":"@scenario10"}]}],"name":"SC10- Logged user could add different products to Wishlist","description":"","id":"sc10--logged-user-could-add-different-products-to-wishlist","keyword":"Feature","uri":"file:src/main/resources/features/SC10-addDifferentProductsToWhishList.feature","tags":[]},{"line":1,"elements":[{"line":2,"name":"","description":"","type":"background","keyword":"Background","steps":[{"result":{"duration":1837000000,"status":"passed"},"line":3,"name":"user navigate to home page","match":{"location":"stepDefinitions.HomePageStepDefinition.openHomePage()"},"keyword":"Given "},{"result":{"duration":1074000000,"status":"passed"},"line":4,"name":"user clicked on login link","match":{"location":"stepDefinitions.LoginStepDefinition.userClickedOnLoginLink()"},"keyword":"And "},{"result":{"duration":101000000,"status":"passed"},"line":5,"name":"user entered email for login","match":{"location":"stepDefinitions.LoginStepDefinition.userEnteredEmailForLogin()"},"keyword":"And "},{"result":{"duration":87000000,"status":"passed"},"line":6,"name":"user entered password for login","match":{"location":"stepDefinitions.LoginStepDefinition.userEnteredPasswordForLogin()"},"keyword":"And "},{"result":{"duration":4163000000,"status":"passed"},"line":7,"name":"user clicked on login button","match":{"location":"stepDefinitions.LoginStepDefinition.userClickedOnLoginButton()"},"keyword":"And "},{"result":{"duration":1303000000,"status":"passed"},"line":8,"name":"user navigate to books pages","match":{"location":"stepDefinitions.AddToShoppingCart.userNavigateToBooksPages()"},"keyword":"And "}]},{"start_timestamp":"2022-09-12T18:31:51.993Z","before":[{"result":{"duration":1567000000,"status":"passed"},"match":{"location":"stepDefinitions.Hooks.openChromeBrowser()"}}],"line":11,"name":"SC11- Logged user could add different products to compare list","description":"","id":"sc11--logged-user-could-add-different-products-to-compare-list;sc11--logged-user-could-add-different-products-to-compare-list","after":[{"result":{"duration":712000000,"status":"passed"},"match":{"location":"stepDefinitions.Hooks.tearDown()"}}],"type":"scenario","keyword":"Scenario","steps":[{"result":{"duration":15209000000,"status":"passed"},"line":13,"name":"user add items to compare list","match":{"location":"stepDefinitions.AddToCompare.userAddItemsToCompareList()"},"keyword":"And "},{"result":{"duration":1384000000,"status":"passed"},"line":14,"name":"user navigate to compare list","match":{"location":"stepDefinitions.AddToCompare.userNavigateToCompareList()"},"keyword":"And "},{"result":{"duration":3095000000,"status":"passed"},"line":15,"name":"added items should appear at compare list","match":{"location":"stepDefinitions.AddToCompare.addedItemsShouldAppearAtCompareList()"},"keyword":"Then "}],"tags":[{"name":"@scenario11"}]}],"name":"SC11- Logged user could add different products to compare list","description":"","id":"sc11--logged-user-could-add-different-products-to-compare-list","keyword":"Feature","uri":"file:src/main/resources/features/SC11-addDifferentProductsToCompareList.feature","tags":[]},{"line":1,"elements":[{"line":3,"name":"","description":"","type":"background","keyword":"Background","steps":[{"result":{"duration":1966000000,"status":"passed"},"line":4,"name":"user navigate to home page","match":{"location":"stepDefinitions.HomePageStepDefinition.openHomePage()"},"keyword":"Given "},{"result":{"duration":1234000000,"status":"passed"},"line":5,"name":"user clicked on login link","match":{"location":"stepDefinitions.LoginStepDefinition.userClickedOnLoginLink()"},"keyword":"And "},{"result":{"duration":100000000,"status":"passed"},"line":6,"name":"user entered email for login","match":{"location":"stepDefinitions.LoginStepDefinition.userEnteredEmailForLogin()"},"keyword":"And "},{"result":{"duration":83000000,"status":"passed"},"line":7,"name":"user entered password for login","match":{"location":"stepDefinitions.LoginStepDefinition.userEnteredPasswordForLogin()"},"keyword":"And "},{"result":{"duration":4183000000,"status":"passed"},"line":8,"name":"user clicked on login button","match":{"location":"stepDefinitions.LoginStepDefinition.userClickedOnLoginButton()"},"keyword":"And "},{"result":{"duration":1008000000,"status":"passed"},"line":9,"name":"user navigate to books pages","match":{"location":"stepDefinitions.AddToShoppingCart.userNavigateToBooksPages()"},"keyword":"And "},{"result":{"duration":15220000000,"status":"passed"},"line":10,"name":"user add items to shopping cart","match":{"location":"stepDefinitions.AddToShoppingCart.userAddItemsToShoppingCart()"},"keyword":"And "},{"result":{"duration":1482000000,"status":"passed"},"line":11,"name":"user navigate to shopping cart","match":{"location":"stepDefinitions.AddToShoppingCart.userNavigateToShopingCart()"},"keyword":"And "},{"result":{"duration":14191000000,"status":"passed"},"line":12,"name":"user complete order","match":{"location":"stepDefinitions.CreateOrder.userCompleteOrder()"},"keyword":"And "}]},{"start_timestamp":"2022-09-12T18:32:22.566Z","before":[{"result":{"duration":1496000000,"status":"passed"},"match":{"location":"stepDefinitions.Hooks.openChromeBrowser()"}}],"line":15,"name":"SC12- Create successful Order","description":"","id":"sc12--create-successful-order;sc12--create-successful-order","after":[{"result":{"duration":745000000,"status":"passed"},"match":{"location":"stepDefinitions.Hooks.tearDown()"}}],"type":"scenario","keyword":"Scenario","steps":[{"result":{"duration":41000000,"status":"passed"},"line":18,"name":"order placed successfully","match":{"location":"stepDefinitions.CreateOrder.orderPlacedSuccessfully()"},"keyword":"Then "}],"tags":[{"name":"@scenario12"}]}],"name":"SC12- Create successful Order","description":"","id":"sc12--create-successful-order","keyword":"Feature","uri":"file:src/main/resources/features/SC12-createOrder.feature","tags":[]}]